ignore_flake8_error.py
ignore_flake8_error-1.0.0.dist-info/LICENSE
ignore_flake8_error-1.0.0.dist-info/METADATA
ignore_flake8_error-1.0.0.dist-info/WHEEL
ignore_flake8_error-1.0.0.dist-info/entry_points.txt
ignore_flake8_error-1.0.0.dist-info/top_level.txt
ignore_flake8_error-1.0.0.dist-info/RECORD
