Metadata-Version: 2.1
Name: ignore-flake8-error
Version: 1.0.0
Summary: add `noqa` comments to ignore every occurrence of a flake8 error
Home-page: https://github.com/samueljsb/ignore-flake8-error
Author: Samuel Searles-Bryant
Author-email: sam@samueljsb.co.uk
License: MIT
Classifier: License :: OSI Approved :: MIT License
Classifier: Programming Language :: Python :: 3
Classifier: Programming Language :: Python :: 3 :: Only
Classifier: Programming Language :: Python :: Implementation :: CPython
Requires-Python: >=3.8
License-File: LICENSE
Requires-Dist: flake8 (>=4)
Requires-Dist: tokenize-rt
